{
  "id": "ruff",
  "name": "ruff",
  "version": "2025.4.25",
  "customizations": {
    "vscode": {
      "settings": {
        "ruff.path": ["/opt/bin/ruff"],
        "[python]": {
          "editor.defaultFormatter": "charliermarsh.ruff"
        }
      },
      "extensions": ["charliermarsh.ruff"]
    },
    "manifest": {
      "dependencies": [
        {
          "name": "ruff",
          "version": "0.11.7",
          "hint": "releases/v?[0-9]+\\.[0-9]+(\\.[0-9]+)?",
          "repository": "github.com/astral-sh/ruff",
          "artifacts": [
            {
              "architecture": "amd64",
              "url": "https://github.com/astral-sh/ruff/releases/download/${VERSION}/ruff-x86_64-unknown-linux-gnu.tar.gz",
              "checksum": "7f448fea7bac3320416d1465219b8bd58828bfef9a3c8398094ca6c09b71148c"
            },
            {
              "architecture": "arm64",
              "url": "https://github.com/astral-sh/ruff/releases/download/${VERSION}/ruff-aarch64-unknown-linux-gnu.tar.gz",
              "checksum": "ccc11afdc3d3d3b146f972645d54a49c819034b8379d190281962bfa80c69389"
            }
          ]
        }
      ]
    }
  }
}
