{
  "id": "uv",
  "name": "uv",
  "version": "2025.7.1",
  "customizations": {
    "manifest": {
      "dependencies": [
        {
          "name": "uv",
          "version": "0.7.18",
          "hint": "releases/v?[0-9]+\\.[0-9]+(\\.[0-9]+)?",
          "repository": "github.com/astral-sh/uv",
          "artifacts": [
            {
              "architecture": "amd64",
              "url": "https://github.com/astral-sh/uv/releases/download/${VERSION}/uv-x86_64-unknown-linux-gnu.tar.gz",
              "checksum": "bcb8093f59eb08539087faf895ea1e794fe3db395de79eb41ddaa41d8c25adf7"
            },
            {
              "architecture": "arm64",
              "url": "https://github.com/astral-sh/uv/releases/download/${VERSION}/uv-aarch64-unknown-linux-gnu.tar.gz",
              "checksum": "2af8d0d963f547deba09c52aca79a26113f0ed5c903c101241fedcac90c2d8f4"
            }
          ]
        }
      ]
    }
  }
}
