{
  "id": "aws2",
  "name": "aws2",
  "version": "2025.6.27",
  "customizations": {
    "manifest": {
      "dependencies": [
        {
          "name": "cli",
          "version": "2.27.45",
          "hint": "tags/v?[0-9]+\\.[0-9]+(\\.[0-9]+)?",
          "repository": "github.com/aws/aws-cli",
          "artifacts": [
            {
              "architecture": "amd64",
              "url": "https://awscli.amazonaws.com/awscli-exe-linux-x86_64-${VERSION}.zip",
              "checksum": "70f301fd24815d1fef10813d8be59a786558fc53a013b6697d5e6398c549fd73"
            },
            {
              "architecture": "arm64",
              "url": "https://awscli.amazonaws.com/awscli-exe-linux-aarch64-${VERSION}.zip",
              "checksum": "02b9c3dc6d505e977bdc74b43308897696c038486289f2d9575a84ff84058e87"
            }
          ]
        }
      ]
    }
  }
}
